{
  "project_info": {
    "project_number": "502138971624",
    "project_id": "turner-app-1302"
  },
  "client": [
    {
      "client_info": {
        "mobilesdk_app_id": "1:502138971624:android:6f76112dd7b2cc78",
        "android_client_info": {
          "package_name": "tripin.com.tripin_shipper"
        }
      },
      "oauth_client": [
        {
          "client_id": "502138971624-utuhpvg6d1vfub3do4t3aah5us0adsdl.apps.googleusercontent.com",
          "client_type": 1,
          "android_info": {
            "package_name": "tripin.com.tripin_shipper",
            "certificate_hash": "5FD0D6A9D3558530B34A4928FF2209AE6A3B2FF7"
          }
        },
        {
          "client_id": "502138971624-os7hefgos0vts2pm4lflq258h47bkjqd.apps.googleusercontent.com",
          "client_type": 3
        }
      ],
      "api_key": [
        {
          "current_key": "AIzaSyDGZGYOayLUO63vwaNl4AZuxBV1sAyWgbw"
        }
      ],
      "services": {
        "analytics_service": {
          "status": 1
        },
        "appinvite_service": {
          "status": 1,
          "other_platform_oauth_client": []
        },
        "ads_service": {
          "status": 1
        }
      }
    }
  ],
  "configuration_version": "1"
}